telemetree/__init__.py
telemetree/client.py
telemetree/config.py
telemetree/constants.py
telemetree/encryption.py
telemetree/exceptions.py
telemetree/http_client.py
telemetree/logging_config.py
telemetree/schemas.py
telemetree/utils.py
test/__init__.py
test/client_test.py
test/encryption_test.py
test/event_builder_test.py
test/fixtures.py
telemetree-0.4.0.dist-info/METADATA
telemetree-0.4.0.dist-info/WHEEL
telemetree-0.4.0.dist-info/top_level.txt
telemetree-0.4.0.dist-info/RECORD
