Metadata-Version: 2.4
Name: telemetree
Version: 0.4.0
Summary: Python SDK for Telegram event tracking and analytics.
Home-page: https://github.com/TONSolutions/telemetree-python
Author: Chris Cherniakov
Author-email: chris@ton.solutions
Classifier: Development Status :: 3 - Alpha
Classifier: Intended Audience :: Developers
Classifier: License :: OSI Approved :: MIT License
Classifier: Programming Language :: Python :: 3
Classifier: Programming Language :: Python :: 3.7
Classifier: Programming Language :: Python :: 3.8
Classifier: Programming Language :: Python :: 3.9
Requires-Dist: setuptools
Requires-Dist: requests
Requires-Dist: pydantic
Requires-Dist: pycryptodome
Requires-Dist: rsa
Requires-Dist: telethon
Dynamic: author
Dynamic: author-email
Dynamic: classifier
Dynamic: description
Dynamic: description-content-type
Dynamic: home-page
Dynamic: requires-dist
Dynamic: summary
